Metadata-Version: 2.1
Name: tesh-GauBiprop
Version: 0.1
Summary: Gaussian and Binomial distributions
Author: Emmanuel Mutegi
Author-email: emmamutegi97@gmail.com
License: UNKNOWN
Platform: UNKNOWN
